libvsc-0.0.1.3625801070.dist-info/entry_points.txt
libvsc-0.0.1.3625801070.dist-info/METADATA
libvsc-0.0.1.3625801070.dist-info/top_level.txt
libvsc-0.0.1.3625801070.dist-info/RECORD
libvsc-0.0.1.3625801070.dist-info/WHEEL
libvsc-0.0.1.3625801070.dist-info/LICENSE
libvsc/__init__.py
libvsc/core.cpython-39-x86_64-linux-gnu.so
