Metadata-Version: 2.1
Name: libvsc
Version: 0.0.1.3625801070
Summary: Core Verification Stimulus and Coverage library
Home-page: https://github.com/fvutils/libvsc
Author: Matthew Ballance
Author-email: matt.ballance@gmail.com
License: Apache 2.0
Keywords: SystemVerilog,Verilog,RTL,Python
License-File: LICENSE
